funchallenge/__init__.py
funchallenge/db/__init__.py
funchallenge/db/base.py
funchallenge/server/__init__.py
funchallenge/server/core.py
funchallenge-0.0.2.dist-info/METADATA
funchallenge-0.0.2.dist-info/WHEEL
funchallenge-0.0.2.dist-info/top_level.txt
funchallenge-0.0.2.dist-info/RECORD
