Metadata-Version: 2.1
Name: funchallenge
Version: 0.0.2
Summary: funchallenge
Home-page: https://github.com/farfarfun/funchallenge
Author: bingtao
Author-email: 1007530194@qq.com
Requires-Dist: sqlalchemy
Requires-Dist: funsecret
Requires-Dist: pymysql
